hepcrawl/__init__.py
hepcrawl/api.py
hepcrawl/dateutils.py
hepcrawl/downloaders.py
hepcrawl/extensions.py
hepcrawl/inputs.py
hepcrawl/items.py
hepcrawl/loaders.py
hepcrawl/mappings.py
hepcrawl/middlewares.py
hepcrawl/outputs.py
hepcrawl/pipelines.py
hepcrawl/scrapy.cfg
hepcrawl/scrapyd.cfg
hepcrawl/settings.py
hepcrawl/tohep.py
hepcrawl/utils.py
hepcrawl/version.py
hepcrawl/extractors/__init__.py
hepcrawl/extractors/jats.py
hepcrawl/extractors/nlm.py
hepcrawl/parsers/__init__.py
hepcrawl/parsers/arxiv.py
hepcrawl/parsers/crossref.py
hepcrawl/parsers/elsevier.py
hepcrawl/parsers/jats.py
hepcrawl/spiders/__init__.py
hepcrawl/spiders/aps_spider.py
hepcrawl/spiders/arxiv_spider.py
hepcrawl/spiders/cds_spider.py
hepcrawl/spiders/crossref_spider.py
hepcrawl/spiders/desy_spider.py
hepcrawl/spiders/edp_spider.py
hepcrawl/spiders/elsevier_spider.py
hepcrawl/spiders/hindawi_spider.py
hepcrawl/spiders/iop_spider.py
hepcrawl/spiders/pos_spider.py
hepcrawl/spiders/wsp_spider.py
hepcrawl/spiders/common/__init__.py
hepcrawl/spiders/common/lastrunstore_spider.py
hepcrawl/spiders/common/oaipmh_spider.py
hepcrawl/testlib/__init__.py
hepcrawl/testlib/celery_monitor.py
hepcrawl/testlib/fixtures.py
hepcrawl/testlib/scrapyd_coverage_runner.py
hepcrawl/testlib/tasks.py
hepcrawl/testlib/utils.py
hepcrawl-13.0.82.dist-info/AUTHORS
hepcrawl-13.0.82.dist-info/LICENSE
hepcrawl-13.0.82.dist-info/METADATA
hepcrawl-13.0.82.dist-info/WHEEL
hepcrawl-13.0.82.dist-info/entry_points.txt
hepcrawl-13.0.82.dist-info/top_level.txt
hepcrawl-13.0.82.dist-info/RECORD
